nnql/__init__.py
nnql/backends/__init__.py
nnql/backends/pytorch/__init__.py
nnql/backends/pytorch/import_hook.py
nnql/backends/tensorflow/__init__.py
nnql/backends/tensorflow/import_hook.py
nnql/capacity.py
nnql/cli.py
nnql/conftest.py
nnql/context.py
nnql/error.py
nnql/executor.py
nnql/graph.py
nnql/import_hook.py
nnql/lang.py
nnql/tests/__init__.py
nnql/tests/inference_vgg16.py
nnql/tests/just_add.py
nnql/tests/just_add_pytorch.py
nnql/tests/just_add_tfe.py
nnql/tests/test_base.py
nnql/tests/test_base_pytorch.py
nnql/tests/test_base_tfe.py
nnql/tests/test_cli.py
nnql/tests/test_dumb.py
nnql/tests/test_effective_path.py
nnql/tests/test_import_hook_tfe.py
nnql/tests/test_op_count.py
nnql/tests/test_op_count_pytorch.py
nnql/tests/test_op_count_tfe.py
nnql/tests/test_print_graph.py
nnql/tests/test_pruning.py
nnql/tests/test_pruning_v2.py
nnql/tests/train_model.py
nnql/tools/__init__.py
nnql/tools/dumb.py
nnql/tools/effective_path.py
nnql/tools/op_count.py
nnql/tools/op_count_naive.py
nnql/tools/print_graph.py
nnql/tools/profiler.py
nnql/tools/pruner.py
nnql/tools/pruner_v2.py
nnql/version.py
nnql-0.1.0.dist-info/entry_points.txt
nnql-0.1.0.dist-info/LICENSE
nnql-0.1.0.dist-info/WHEEL
nnql-0.1.0.dist-info/METADATA
nnql-0.1.0.dist-info/RECORD
